sngraz/__init__.py
sngraz/certchain.crt
sngraz/sngraz.py
stromnetzgraz-0.1.8.dist-info/LICENSE
stromnetzgraz-0.1.8.dist-info/METADATA
stromnetzgraz-0.1.8.dist-info/WHEEL
stromnetzgraz-0.1.8.dist-info/top_level.txt
stromnetzgraz-0.1.8.dist-info/RECORD
