Metadata-Version: 2.1
Name: stromnetzgraz
Version: 0.1.8
Summary: Python client library for Stromnetz Graz API
Home-page: https://github.com/dreautall/stromnetzgraz
Author: dreautall
Author-email: michael@online-net.eu
Project-URL: Documentation, https://github.com/dreautall/stromnetzgraz
Project-URL: Bug Reports, https://github.com/dreautall/stromnetzgraz/issues
Project-URL: Source Code, https://github.com/dreautall/stromnetzgraz
Keywords: stromnetz graz,power,api
Classifier: Development Status :: 5 - Production/Stable
Classifier: Intended Audience :: Developers
Classifier: Programming Language :: Python :: 3
Classifier: Programming Language :: Python :: 3.6
Classifier: Programming Language :: Python :: 3.7
Classifier: Programming Language :: Python :: 3.8
Classifier: Programming Language :: Python :: 3.9
Classifier: Programming Language :: Python :: 3 :: Only
Classifier: License :: OSI Approved :: MIT License
Classifier: Operating System :: OS Independent
Requires-Python: >=3.6
License-File: LICENSE
Requires-Dist: pyjwt
Requires-Dist: aiohttp
Provides-Extra: dev
Requires-Dist: check-manifest ; extra == 'dev'
